{"http://creativecommons.org/ns#attributionName": ["Arbeitsbereich Wissenschaftliche IT, digitale Plattformen und Tools des RGZM"], "http://creativecommons.org/ns#attributionURL": ["http://www.wikidata.org/entity/Q115264627"], "http://creativecommons.org/ns#license": ["http://creativecommons.org/licenses/by-sa/4.0/"], "http://purl.org/dc/terms/identifier": ["http://data.archaeology.link/data/maritimethesaurus/"], "http://purl.org/dc/terms/issued": ["2022-11-18T13:14:49.003510+00:00"], "http://purl.org/dc/terms/publisher": ["http://www.wikidata.org/entity/Q115264627"], "http://www.w3.org/1999/02/22-rdf-syntax-ns#type": ["http://www.w3.org/2004/02/skos/core#Concept"], "http://www.w3.org/2000/01/rdf-schema#label": ["Krigsudstyr", "Warfare", "Krigsudstyr", "Oorlogvoering", "Guerre", "Guerra", "material e aparejo de guerra", "Uzbrojenie", "\u0395\u03c7\u03b8\u03c1\u03bf\u03c0\u03c1\u03b1\u03be\u03af\u03b5\u03c2", "\u05dc\u05d5\u05d7\u05de\u05d4; \u05de\u05dc\u05d7\u05de\u05d4"], "http://www.w3.org/2004/02/skos/core#inScheme": ["http://data.archaeology.link/data/maritimethesaurus/cs01"], "http://www.w3.org/2004/02/skos/core#narrower": ["http://data.archaeology.link/data/maritimethesaurus/2634", "http://data.archaeology.link/data/maritimethesaurus/2632", "http://data.archaeology.link/data/maritimethesaurus/2633", "http://data.archaeology.link/data/maritimethesaurus/2635", "http://data.archaeology.link/data/maritimethesaurus/2637", "http://data.archaeology.link/data/maritimethesaurus/2636"], "http://www.w3.org/2004/02/skos/core#note": ["This is a parent Concept of NAVIS I or NAVIS II."], "http://www.w3.org/2004/02/skos/core#prefLabel": ["Krigsudstyr", "Warfare", "Krigsudstyr", "Oorlogvoering", "Guerre", "Guerra", "material e aparejo de guerra", "Uzbrojenie", "\u0395\u03c7\u03b8\u03c1\u03bf\u03c0\u03c1\u03b1\u03be\u03af\u03b5\u03c2", "\u05dc\u05d5\u05d7\u05de\u05d4; \u05de\u05dc\u05d7\u05de\u05d4"], "http://www.w3.org/2004/02/skos/core#topConceptOf": ["http://data.archaeology.link/data/maritimethesaurus/cs01"], "http://www.w3.org/ns/prov#wasAttributedTo": ["http://data.archaeology.link/data/maritimethesaurus/ImportPythonScript"], "http://www.w3.org/ns/prov#wasDerivedFrom": ["http://www.wikidata.org/entity/Q115264680"], "http://www.w3.org/ns/prov#wasGeneratedBy": ["http://data.archaeology.link/data/maritimethesaurus/activity_1015"]}